tp2ctl/__init__.py
tp2ctl/tp2ctl.py
tp2ctl-1.0.1.dist-info/LICENSE
tp2ctl-1.0.1.dist-info/METADATA
tp2ctl-1.0.1.dist-info/WHEEL
tp2ctl-1.0.1.dist-info/entry_points.txt
tp2ctl-1.0.1.dist-info/top_level.txt
tp2ctl-1.0.1.dist-info/RECORD
