Metadata-Version: 2.1
Name: tp2ctl
Version: 1.0.1
Summary: Control IBM Trackpoint 2 Keyboard features (Trackpoint sensitivity, ...)
Home-page: https://github.com/telecastr/tp2ctl
Author: telecastr
Author-email: telecastr@protonmail.com
License: UNKNOWN
Platform: UNKNOWN
Classifier: Programming Language :: Python :: 3
Classifier: License :: OSI Approved :: MIT License
Classifier: Operating System :: POSIX :: Linux
Requires-Python: >=3
License-File: LICENSE
